numpriev/__init__.py
numpriev-1.0.dist-info/LICENSE
numpriev-1.0.dist-info/METADATA
numpriev-1.0.dist-info/WHEEL
numpriev-1.0.dist-info/top_level.txt
numpriev-1.0.dist-info/RECORD
